{"entity_id":"abdullah-mohtadi-named-in-mahsa-amini-protests-2022","from_entity":"abdullah-mohtadi","to_entity":"mahsa-amini-protests-2022","type":"named-in","confidence":"confirmed","date_from":"2022","date_to":null,"evidence":[{"source_url":"https://en.wikipedia.org/wiki/Komala_Party_of_Iranian_Kurdistan","source_title":"Komala Party of Iranian Kurdistan — Wikipedia","source_date":"2026-04-11","description":"Mohtadi participated in opposition coordination during the Mahsa Amini protests"}],"intermediaries":[],"symmetric":false,"family_subtype":null,"editorial_notes":"Active in diaspora opposition coordination during protests"}
