{"entity_id":"fadaiyan-e-khalq-minority-opposed-fadaiyan-e-khalq-majority","from_entity":"fadaiyan-e-khalq-minority","to_entity":"fadaiyan-e-khalq-majority","type":"opposed","confidence":"confirmed","date_from":"1980","date_to":null,"evidence":[{"source_url":"https://en.wikipedia.org/wiki/Organization_of_Iranian_People%27s_Fedai_Guerrillas","source_title":"OIPFG — Wikipedia","source_date":"2026-04-11","description":"The Minority faction rejected the Majority's pro-Soviet line and collaboration with the Islamic Republic"}],"intermediaries":[],"symmetric":false,"family_subtype":null,"editorial_notes":"Ideological split in 1980 over Soviet alignment"}
