{
  "entity_id": "mehdi-rahimi-subject-of-post-revolution-executions-1979",
  "from_entity": "mehdi-rahimi",
  "to_entity": "post-revolution-executions-1979",
  "type": "subject-of",
  "confidence": "confirmed",
  "symmetric": false,
  "family_subtype": null,
  "notes": "Military governor of Tehran, executed in post-revolution tribunals",
  "evidence": [
    {
      "source_url": "https://en.wikipedia.org/wiki/Islamic_Revolutionary_Court",
      "source_title": "Revolutionary Courts — Wikipedia",
      "source_date": "2024-01-01"
    }
  ]
}