{
  "entity_id": "mohammad-marandi-affiliated-with-irgc",
  "from_entity": "mohammad-marandi",
  "to_entity": "islamic-revolutionary-guard-corps",
  "type": "affiliated-with",
  "confidence": "confirmed",
  "date_from": null,
  "date_to": null,
  "evidence": [
    {
      "source_url": "https://www.thejc.com/news/uk/photo-reveals-iranian-academic-platformed-by-bbc-as-proud-irgc-fighter-ong4d3lo",
      "source_title": "BBC Iranian expert who ranted about 'chosen people' pictured in IRGC uniform",
      "source_date": "2024-10-11",
      "description": "The Jewish Chronicle published a photograph of Mohammad Marandi wearing IRGC military uniform beside the IRGC logo, establishing ties to the Revolutionary Guards beyond his academic and advisory roles."
    }
  ],
  "intermediaries": [],
  "symmetric": false,
  "family_subtype": null,
  "editorial_notes": ""
}
