{
  "entity_id": "parviz-fattah-member-of-islamic-revolutionary-guard-corps",
  "from_entity": "parviz-fattah",
  "to_entity": "islamic-revolutionary-guard-corps",
  "type": "member-of",
  "confidence": "confirmed",
  "date_from": null,
  "date_to": null,
  "evidence": [
    {
      "source_url": "https://home.treasury.gov/news/press-releases/tg1010",
      "source_title": "Treasury Designates Iranian Entities Tied to the IRGC and IRISL — US Treasury",
      "source_date": "2010-12-21",
      "description": "Former IRGC member, deputy commander of Khatam al-Anbiya"
    }
  ],
  "intermediaries": [],
  "symmetric": false,
  "family_subtype": null,
  "editorial_notes": ""
}
